ba/agent.py
ba/ba.py
ba/models.py
ba/thread.py
ba/tools.py
ba/utils.py
ba/api/agents.py
ba/api/threads.py
ba/api/utils.py
belaraby_ai_sdk-0.2.1.dist-info/METADATA
belaraby_ai_sdk-0.2.1.dist-info/WHEEL
belaraby_ai_sdk-0.2.1.dist-info/licenses/LICENSE
belaraby_ai_sdk-0.2.1.dist-info/RECORD
