Metadata-Version: 2.4
Name: belaraby-ai-sdk
Version: 0.2.1
Summary: BelArabyAI SDK - A Python SDK for creating and managing AI Workers
Project-URL: Homepage, https://belaraby.ai
Project-URL: Documentation, https://docs.belaraby.ai
Project-URL: Repository, https://github.com/rhkiswani/BelArabyAI-python-sdk
Project-URL: Issues, https://github.com/rhkiswani/BelArabyAI-python-sdk/issues
Author-email: BelArabyAI Team <mk@belaraby.com>
License: MIT License
License-File: LICENSE
Keywords: agent,ai,automation,llm,mcp,worker
Classifier: Development Status :: 4 - Beta
Classifier: Intended Audience :: Developers
Classifier: License :: OSI Approved :: MIT License
Classifier: Operating System :: OS Independent
Classifier: Programming Language :: Python :: 3
Classifier: Programming Language :: Python :: 3.11
Classifier: Programming Language :: Python :: 3.12
Classifier: Programming Language :: Python :: 3.13
Classifier: Topic :: Scientific/Engineering :: Artificial Intelligence
Classifier: Topic :: Software Development :: Libraries :: Python Modules
Requires-Python: >=3.11
Requires-Dist: defusedxml>=0.7.1
Requires-Dist: fastmcp>=2.10.6
Requires-Dist: httpx>=0.28.1
Requires-Dist: pydantic>=2.0.0
Provides-Extra: dev
Requires-Dist: black>=23.0.0; extra == 'dev'
Requires-Dist: isort>=5.12.0; extra == 'dev'
Requires-Dist: mypy>=1.0.0; extra == 'dev'
Requires-Dist: pytest-asyncio>=0.21.0; extra == 'dev'
Requires-Dist: pytest-cov>=4.0.0; extra == 'dev'
Requires-Dist: pytest>=7.0.0; extra == 'dev'
Requires-Dist: python-dotenv>=1.0.0; extra == 'dev'
Requires-Dist: ruff>=0.1.0; extra == 'dev'
